README.md
setup.py
PyRAML.egg-info/PKG-INFO
PyRAML.egg-info/SOURCES.txt
PyRAML.egg-info/dependency_links.txt
PyRAML.egg-info/namespace_packages.txt
PyRAML.egg-info/requires.txt
PyRAML.egg-info/top_level.txt
PyRAML.egg-info/zip-safe
lib/__init__.py
lib/api.py
lib/converter.py
lib/errors.py
lib/loader.py
lib/parser.py